aiopyarr/__init__.py
aiopyarr/const.py
aiopyarr/exceptions.py
aiopyarr/lidarr_client.py
aiopyarr/py.typed
aiopyarr/radarr_client.py
aiopyarr/readarr_client.py
aiopyarr/request_client.py
aiopyarr/sonarr_client.py
aiopyarr/models/__init__.py
aiopyarr/models/base.py
aiopyarr/models/const.py
aiopyarr/models/host_configuration.py
aiopyarr/models/lidarr.py
aiopyarr/models/lidarr_common.py
aiopyarr/models/radarr.py
aiopyarr/models/radarr_common.py
aiopyarr/models/readarr.py
aiopyarr/models/readarr_common.py
aiopyarr/models/request.py
aiopyarr/models/request_common.py
aiopyarr/models/sonarr.py
aiopyarr/models/sonarr_common.py
aiopyarr-23.4.0.dist-info/LICENSE
aiopyarr-23.4.0.dist-info/METADATA
aiopyarr-23.4.0.dist-info/WHEEL
aiopyarr-23.4.0.dist-info/top_level.txt
aiopyarr-23.4.0.dist-info/RECORD
