Metadata-Version: 2.1
Name: aiopyarr
Version: 23.4.0
Summary: An Asynchronous Lidarr, Radarr, Readarr, Sonarr APIs for Python.
Home-page: https://github.com/tkdrob/aiopyarr
Author: Robert Hillis
Author-email: tkdrob4390@yahoo.com
License: MIT license
Keywords: aiopyarr,radarr,sonarr,plex
Classifier: Intended Audience :: Developers
Classifier: License :: OSI Approved :: MIT License
Classifier: Natural Language :: English
Classifier: Operating System :: OS Independent
Classifier: Programming Language :: Python :: 3
Classifier: Programming Language :: Python :: 3.9
Classifier: Programming Language :: Python :: 3.10
Classifier: Topic :: Software Development :: Libraries :: Python Modules
Requires-Python: >=3.9
License-File: LICENSE
